Metadata-Version: 2.1
Name: epubs
Version: 0.0.3
Summary: A Conversion Tool for EPUB
Home-page: https://gitee.com/maxbanana
Author: hongbo liu
Author-email: 782027465@qq.com
License: Apache
Platform: UNKNOWN
Classifier: Programming Language :: Python :: 3
Classifier: License :: OSI Approved :: Apache Software License
Classifier: Operating System :: OS Independent
Requires-Python: >=3.6
License-File: LICENSE
